hello_world/__init__.py
hello_world/tools/__init__.py
hello_world/tools/hello_world_tool.py
hello_world/tools/utils.py
hello_world/yamls/hello_world_tool.yaml
tests/__init__.py
tests/test_hello_world_tool.py
asim_hello_world-0.0.1.dist-info/METADATA
asim_hello_world-0.0.1.dist-info/WHEEL
asim_hello_world-0.0.1.dist-info/entry_points.txt
asim_hello_world-0.0.1.dist-info/top_level.txt
asim_hello_world-0.0.1.dist-info/RECORD
