Metadata-Version: 2.1
Name: asim_hello_world
Version: 0.0.1
Summary: This is my tools package
